cktgym_discovery_client/__init__.py
cktgym_discovery_client/gradient_descent.py
cktgym_discovery_client/user.py
cktgym_discovery_client/auth/__init__.py
cktgym_discovery_client/auth/errors/__init__.py
cktgym_discovery_client/errors/__init__.py
cktgym_discovery_client/mock/__init__.py
discovery_client/__init__.py
discovery_client/gradient_descent.py
discovery_client/user.py
discovery_client/auth/__init__.py
discovery_client/auth/errors/__init__.py
discovery_client/errors/__init__.py
discovery_client/mock/__init__.py
cktgym_discovery_client-0.0.4.dist-info/METADATA
cktgym_discovery_client-0.0.4.dist-info/WHEEL
cktgym_discovery_client-0.0.4.dist-info/top_level.txt
cktgym_discovery_client-0.0.4.dist-info/RECORD
